timerun.py
timerun-0.4.0.dist-info/licenses/LICENSE
timerun-0.4.0.dist-info/METADATA
timerun-0.4.0.dist-info/WHEEL
timerun-0.4.0.dist-info/top_level.txt
timerun-0.4.0.dist-info/zip-safe
timerun-0.4.0.dist-info/RECORD
