Metadata-Version: 2.4
Name: timerun
Version: 0.4.0
Summary: TimeRun is a Python library for elapsed time measurement.
Author-email: HH-MWB <h.hong@mail.com>
License: MIT
Project-URL: Homepage, https://github.com/HH-MWB/timerun
Project-URL: Bug Reports, https://github.com/HH-MWB/timerun/issues
Project-URL: Changelog, https://github.com/HH-MWB/timerun/releases
Project-URL: PyPI, https://pypi.org/project/timerun
Keywords: time,measurement,elapsed,stopwatch,timer,performance
Classifier: Development Status :: 3 - Alpha
Classifier: Intended Audience :: Developers
Classifier: License :: OSI Approved :: MIT License
Classifier: Operating System :: OS Independent
Classifier: Programming Language :: Python :: 3
Classifier: Programming Language :: Python :: 3.9
Classifier: Programming Language :: Python :: 3.10
Classifier: Programming Language :: Python :: 3.11
Classifier: Programming Language :: Python :: 3.12
Classifier: Programming Language :: Python :: 3.13
Classifier: Programming Language :: Python :: 3.14
Classifier: Topic :: Software Development :: Libraries :: Python Modules
Classifier: Topic :: System :: Monitoring
Requires-Python: >=3.9
License-File: LICENSE
Provides-Extra: dev
Requires-Dist: pytest; extra == "dev"
Requires-Dist: pytest-asyncio; extra == "dev"
Requires-Dist: pytest-cov; extra == "dev"
Dynamic: license-file
